barenames/__init__.py
barenames/__main__.py
barenames/lib/__init__.py
barenames-0.1.2.dist-info/entry_points.txt
barenames-0.1.2.dist-info/LICENSE
barenames-0.1.2.dist-info/WHEEL
barenames-0.1.2.dist-info/METADATA
barenames-0.1.2.dist-info/RECORD
