Metadata-Version: 2.1
Name: barenames
Version: 0.1.2
Summary: Batch file rename tool
Home-page: https://github.com/cmd410/barenames
License: LGPL-2.1-only
Author: Crystal Melting Dot
Author-email: stresspassing@gmail.com
Requires-Python: >=3.9,<4.0
Classifier: License :: OSI Approved
Classifier: Programming Language :: Python :: 3
Classifier: Programming Language :: Python :: 3.9
Requires-Dist: click (>=8.0.1,<9.0.0)
Project-URL: Repository, https://github.com/cmd410/barenames
